docs/conf.py
ssim/__init__.py
ssim/dssutil.py
ssim/ems.py
ssim/grid.py
ssim/heuristicems.py
ssim/loads.py
ssim/metrics.py
ssim/opendss.py
ssim/reliability.py
ssim/storage.py
ssim/federates/__init__.py
ssim/federates/ems.json
ssim/federates/ems.py
ssim/federates/grid.json
ssim/federates/loads.py
ssim/federates/logger.json
ssim/federates/logger.py
ssim/federates/metrics.json
ssim/federates/metrics.py
ssim/federates/opendss.py
ssim/federates/reliability.json
ssim/federates/reliability.py
ssim/federates/storage.json
ssim/federates/storage.py
ssim/federates/timing.py
ssim/tests/__init__.py
ssim/tests/conftest.py
ssim/tests/test_der_control.py
ssim/tests/test_dssutil.py
ssim/tests/test_ems.py
ssim/tests/test_grid.py
ssim/tests/test_hashing.py
ssim/tests/test_metrics.py
ssim/tests/test_opendss.py
ssim/tests/test_reilability.py
ssim/tests/test_storage_control.py
ssim/ui/__init__.py
ssim/ui/core.py
ssim/ui/kivy/common.kv
ssim/ui/kivy/control.py
ssim/ui/kivy/ssim.kv
ssim/ui/kivy/ssimapp.py
ssim/ui/kivy/util.py
ssim/ui/kivy/xygrid.py
ssim/ui/kivy/fonts/Exo2-Black.ttf
ssim/ui/kivy/fonts/Exo2-BlackItalic.ttf
ssim/ui/kivy/fonts/Exo2-Bold.ttf
ssim/ui/kivy/fonts/Exo2-BoldItalic.ttf
ssim/ui/kivy/fonts/Exo2-ExtraBold.ttf
ssim/ui/kivy/fonts/Exo2-ExtraBoldItalic.ttf
ssim/ui/kivy/fonts/Exo2-ExtraLight.ttf
ssim/ui/kivy/fonts/Exo2-ExtraLightItalic.ttf
ssim/ui/kivy/fonts/Exo2-Italic.ttf
ssim/ui/kivy/fonts/Exo2-Light.ttf
ssim/ui/kivy/fonts/Exo2-LightItalic.ttf
ssim/ui/kivy/fonts/Exo2-Medium.ttf
ssim/ui/kivy/fonts/Exo2-MediumItalic.ttf
ssim/ui/kivy/fonts/Exo2-Regular.ttf
ssim/ui/kivy/fonts/Exo2-SemiBold.ttf
ssim/ui/kivy/fonts/Exo2-SemiBoldItalic.ttf
ssim/ui/kivy/fonts/Exo2-Thin.ttf
ssim/ui/kivy/fonts/Exo2-ThinItalic.ttf
ssim/ui/kivy/fonts/LICENSE.txt
ssim/ui/kivy/fonts/OFL.txt
ssim/ui/kivy/fonts/OpenSans-Bold.ttf
ssim/ui/kivy/fonts/OpenSans-BoldItalic.ttf
ssim/ui/kivy/fonts/OpenSans-ExtraBold.ttf
ssim/ui/kivy/fonts/OpenSans-ExtraBoldItalic.ttf
ssim/ui/kivy/fonts/OpenSans-Italic.ttf
quest_ssim-1.0.0b4.dist-info/LICENSE
quest_ssim-1.0.0b4.dist-info/METADATA
quest_ssim-1.0.0b4.dist-info/WHEEL
quest_ssim-1.0.0b4.dist-info/entry_points.txt
quest_ssim-1.0.0b4.dist-info/top_level.txt
quest_ssim-1.0.0b4.dist-info/RECORD
